Image_/__init__.py
Image_/image_processing.py
organize/__init__.py
organize/organize_hard.py
ProcImage-0.0.1.dist-info/LICENSE.txt
ProcImage-0.0.1.dist-info/METADATA
ProcImage-0.0.1.dist-info/WHEEL
ProcImage-0.0.1.dist-info/dependency_links.txt
ProcImage-0.0.1.dist-info/top_level.txt
ProcImage-0.0.1.dist-info/RECORD
