Metadata-Version: 2.1
Name: ProcImage
Version: 0.0.1
Summary: A small example package
Home-page: https://github.com/Alaa-Jassim/ProcImage
Author: Alaa Jassim Mohammed
Author-email: Alaa Jassim Mohammed <alaapypi@gmail.com>
Project-URL: Homepage, https://github.com/Alaa-Jassim/proc-image.git
Project-URL: Bug Tracker, https://github.com/Alaa-Jassim/proc-image.git
Classifier: Programming Language :: Python :: 3
Classifier: License :: OSI Approved :: MIT License
Classifier: Operating System :: OS Independent
Requires-Python: >=3.10
License-File: LICENSE.txt
Requires-Dist: Pillow
Requires-Dist: prettytable
